{"expireTime":1694535128811,"key":"github.com GET /search/issues q=Empty states+repo:carbon-design-system/carbon+is:issue+is:open+in:title","val":{"total_count":1,"incomplete_results":false,"items":[{"url":"https://api.github.com/repos/carbon-design-system/carbon/issues/10813","repository_url":"https://api.github.com/repos/carbon-design-system/carbon","labels_url":"https://api.github.com/repos/carbon-design-system/carbon/issues/10813/labels{/name}","comments_url":"https://api.github.com/repos/carbon-design-system/carbon/issues/10813/comments","events_url":"https://api.github.com/repos/carbon-design-system/carbon/issues/10813/events","html_url":"https://github.com/carbon-design-system/carbon/issues/10813","id":1146258819,"node_id":"I_kwDOBQ58z85EUoWD","number":10813,"title":"Keeping column headers in empty states","user":{"login":"thefirstartist","id":40870771,"node_id":"MDQ6VXNlcjQwODcwNzcx","avatar_url":"https://avatars.githubusercontent.com/u/40870771?v=4","gravatar_id":"","url":"https://api.github.com/users/thefirstartist","html_url":"https://github.com/thefirstartist","followers_url":"https://api.github.com/users/thefirstartist/followers","following_url":"https://api.github.com/users/thefirstartist/following{/other_user}","gists_url":"https://api.github.com/users/thefirstartist/gists{/gist_id}","starred_url":"https://api.github.com/users/thefirstartist/starred{/owner}{/repo}","subscriptions_url":"https://api.github.com/users/thefirstartist/subscriptions","organizations_url":"https://api.github.com/users/thefirstartist/orgs","repos_url":"https://api.github.com/users/thefirstartist/repos","events_url":"https://api.github.com/users/thefirstartist/events{/privacy}","received_events_url":"https://api.github.com/users/thefirstartist/received_events","type":"User","site_admin":false},"labels":[{"id":1056028594,"node_id":"MDU6TGFiZWwxMDU2MDI4NTk0","url":"https://api.github.com/repos/carbon-design-system/carbon/labels/role:%20ux%20%F0%9F%8D%BF","name":"role: ux 🍿","color":"82cfff","default":false,"description":""},{"id":1056028599,"node_id":"MDU6TGFiZWwxMDU2MDI4NTk5","url":"https://api.github.com/repos/carbon-design-system/carbon/labels/type:%20docs%20%F0%9F%93%96","name":"type: docs 📖","color":"3ddbd9","default":false,"description":""},{"id":1056028600,"node_id":"MDU6TGFiZWwxMDU2MDI4NjAw","url":"https://api.github.com/repos/carbon-design-system/carbon/labels/role:%20visual%20%F0%9F%8E%A8","name":"role: visual 🎨","color":"82cfff","default":false,"description":""},{"id":1056028605,"node_id":"MDU6TGFiZWwxMDU2MDI4NjA1","url":"https://api.github.com/repos/carbon-design-system/carbon/labels/status:%20help%20wanted%20%F0%9F%91%90","name":"status: help wanted 👐","color":"8a3ffc","default":false,"description":""},{"id":1056028613,"node_id":"MDU6TGFiZWwxMDU2MDI4NjEz","url":"https://api.github.com/repos/carbon-design-system/carbon/labels/type:%20a11y%20%E2%99%BF","name":"type: a11y ♿","color":"3ddbd9","default":false,"description":""},{"id":1733171961,"node_id":"MDU6TGFiZWwxNzMzMTcxOTYx","url":"https://api.github.com/repos/carbon-design-system/carbon/labels/proposal:%20open","name":"proposal: open","color":"6fdc8c","default":false,"description":"This request has gone through triaging. We're determining whether we take this on or not."},{"id":1733200991,"node_id":"MDU6TGFiZWwxNzMzMjAwOTkx","url":"https://api.github.com/repos/carbon-design-system/carbon/labels/type:%20pattern%20%F0%9F%92%A0","name":"type: pattern 💠","color":"3ddbd9","default":false,"description":""}],"state":"open","locked":false,"assignee":null,"assignees":[],"milestone":null,"comments":20,"created_at":"2022-02-21T22:00:49Z","updated_at":"2022-08-25T06:15:30Z","closed_at":null,"author_association":"MEMBER","active_lock_reason":null,"body":"### Package\n\ncarbon-components\n\n### Browser\n\nChrome\n\n### Operating System\n\nMacOS\n\n### Package version\n\nV11\n\n### React version\n\nV11\n\n### Automated testing tool and ruleset\n\nn/a\n\n### Assistive technology\n\nn/a\n\n### Description\n\nIn Carbon's Empty states page, it says \"an empty state for a table would replace the table and the column headers and footer should not be present.\" The reason for hiding the column headers is to avoid \"having a screen reader read the entire table before getting to the message that there is no content in the table.\"\r\n<img width=\"922\" alt=\"image\" src=\"https://user-images.githubusercontent.com/40870771/155029822-41dceed1-d6b3-488e-a3e9-94e03554c3ce.png\">\r\nColumn headers are important for sighted users. It shows you what the platform could look like once you’ve input more of your data. [This article](https://userpilot.com/blog/bad-ux-design/) even suggests that empty states should always be replaced with demo content.\r\nWe can hide column headers from a screen reader and display it visually, use the aria-hidden attribute and set it to true.\n\n### WCAG 2.1 Violation\n\n_No response_\n\n### CodeSandbox example\n\nn/a\n\n### Steps to reproduce\n\nn/a\n\n### Code of Conduct\n\n- [X] I agree to follow this project's [Code of Conduct](https://github.com/carbon-design-system/carbon/blob/f555616971a03fd454c0f4daea184adf41fff05b/.github/CODE_OF_CONDUCT.md)\n- [X] I checked the [current issues](https://github.com/carbon-design-system/carbon/issues) for duplicate problems","reactions":{"url":"https://api.github.com/repos/carbon-design-system/carbon/issues/10813/reactions","total_count":0,"+1":0,"-1":0,"laugh":0,"hooray":0,"confused":0,"heart":0,"rocket":0,"eyes":0},"timeline_url":"https://api.github.com/repos/carbon-design-system/carbon/issues/10813/timeline","performed_via_github_app":null,"state_reason":null,"score":1}]}}